nonebot_plugin_makemidi/__init__.py
nonebot_plugin_makemidi/resources/gm.sf2
nonebot_plugin_makemidi/resources/midi/1048421623.mid
nonebot_plugin_makemidi/resources/midi/1048421623.wav
nonebot_plugin_makemidi/utils.py
nonebot_plugin_makemidi-0.3.2.dist-info/METADATA
nonebot_plugin_makemidi-0.3.2.dist-info/WHEEL
nonebot_plugin_makemidi-0.3.2.dist-info/RECORD
