Metadata-Version: 2.1
Name: nonebot_plugin_makemidi
Version: 0.3.2
Summary: Easy midi maker
License: MIT
Author: RandomEnch
Author-email: randomench@foxmail.com
Requires-Python: >=3.8,<4.0
Classifier: License :: OSI Approved :: MIT License
Classifier: Programming Language :: Python :: 3
Classifier: Programming Language :: Python :: 3.8
Classifier: Programming Language :: Python :: 3.9
Classifier: Programming Language :: Python :: 3.10
Classifier: Programming Language :: Python :: 3.11
Classifier: Programming Language :: Python :: 3.12
Classifier: Programming Language :: Python :: 3.13
Requires-Dist: fluidsynth (>=0.2,<0.3)
Requires-Dist: midi2audio (>=0.1.1,<0.2.0)
Requires-Dist: midiutil (>=1.2.1,<2.0.0)
Requires-Dist: nonebot-adapter-onebot (>=2.2.1,<3.0.0)
Requires-Dist: nonebot2 (>=2.0.0rc3,<3.0.0)
Requires-Dist: pydub (>=0.25.1,<0.26.0)
